aqdefreader/__init__.py
aqdefreader/characteristic.py
aqdefreader/file.py
aqdefreader/measurement.py
aqdefreader/operations.py
aqdefreader/part.py
aqdefreader/tests/__init__.py
aqdefreader/tests/test_characteristics.py
aqdefreader/tests/test_file.py
aqdefreader/tests/test_measurements.py
aqdefreader/tests/test_operations.py
aqdefreader/tests/test_operations_dfq.py
aqdefreader/tests/test_parts.py
aqdefreader/tests/testdata.py
aqdefreader-1.3.0.dist-info/licenses/LICENSE
aqdefreader-1.3.0.dist-info/METADATA
aqdefreader-1.3.0.dist-info/WHEEL
aqdefreader-1.3.0.dist-info/top_level.txt
aqdefreader-1.3.0.dist-info/RECORD
