Metadata-Version: 2.4
Name: aqdefreader
Version: 1.3.0
Summary: A module to read DFQ files in the Q-DAS ASCII transfer format.
Home-page: https://github.com/successfactory/aqdef-reader
Author: successfactory consulting group
Author-email: office@successfactory.cc
Classifier: Programming Language :: Python :: 3
Classifier: License :: OSI Approved :: Apache Software License
Classifier: Operating System :: OS Independent
Requires-Python: >=3.6
License-File: LICENSE
Dynamic: author
Dynamic: author-email
Dynamic: classifier
Dynamic: description
Dynamic: home-page
Dynamic: license-file
Dynamic: requires-python
Dynamic: summary
